untrace/__init__.py
untrace/client.py
untrace/exceptions.py
untrace_sdk-0.1.0.dist-info/METADATA
untrace_sdk-0.1.0.dist-info/WHEEL
untrace_sdk-0.1.0.dist-info/RECORD
